event_listener/__init__.py
event_listener/event_listener.py
event_listener/logger.py
event_listener-0.2.dist-info/METADATA
event_listener-0.2.dist-info/WHEEL
event_listener-0.2.dist-info/top_level.txt
event_listener-0.2.dist-info/RECORD
