Metadata-Version: 2.1
Name: event-listener
Version: 0.2
Summary: A kafka event listener to make action dispatching easier
Home-page: https://github.com/aniketpt/event_listener
Author: Aniket Tiratkar
Author-email: atiratkar@gmail.com
License: UNKNOWN
Platform: UNKNOWN
Requires-Dist: aiokafka ==0.10.0
Requires-Dist: pydantic ==2.6.4
Requires-Dist: wheel ==0.43.0
